simpl_users/__init__.py
simpl_users/adapters.py
simpl_users/admin.py
simpl_users/apps.py
simpl_users/factories.py
simpl_users/forms.py
simpl_users/models.py
simpl_users/permissions.py
simpl_users/apis/__init__.py
simpl_users/apis/serializers.py
simpl_users/apis/urls.py
simpl_users/apis/views.py
simpl_users/migrations/0001_initial.py
simpl_users/migrations/0002_auto_20190810_1620.py
simpl_users/migrations/__init__.py
simpl_users/tests/__init__.py
simpl_users/tests/factories.py
simpl_users/tests/test_admin.py
simpl_users/tests/test_api_views.py
simpl_users/tests/test_models.py
simpl_users/tests/test_settings.py
simpl_users/tests/urls.py
simpl_users-0.8.4.dist-info/LICENSE
simpl_users-0.8.4.dist-info/METADATA
simpl_users-0.8.4.dist-info/WHEEL
simpl_users-0.8.4.dist-info/top_level.txt
simpl_users-0.8.4.dist-info/RECORD
