Metadata-Version: 2.1
Name: simpl-users
Version: 0.8.4
Summary: simpl-users provides Simpl Users
Home-page: https://github.com/simplworld/simpl-users
Author: Jeff Triplett
Author-email: jeff@revsys.com
License: UNKNOWN
Platform: UNKNOWN
Classifier: Development Status :: 4 - Beta
Classifier: Environment :: Web Environment
Classifier: Intended Audience :: Developers
Classifier: License :: OSI Approved :: GNU General Public License v2 (GPLv2)
Classifier: Operating System :: OS Independent
Classifier: Programming Language :: Python :: 3
Classifier: Framework :: Django
Requires-Dist: django-username-email (==2.2.4)
